training/__init__.py
training/arguments.py
training/data/phone2idx.json
training/data/speaker2idx.json
vocex/__init__.py
vocex/conformer_layer.py
vocex/conformer_model.py
vocex/scaler.py
vocex/tpu_metrics_delta.py
vocex/transformer.py
vocex/utils.py
voxspex-0.1.0.dist-info/METADATA
voxspex-0.1.0.dist-info/WHEEL
voxspex-0.1.0.dist-info/RECORD
