Metadata-Version: 2.1
Name: voxspex
Version: 0.1.0
Author-Email: Christoph Minixhofer <christoph.minixhofer@gmail.com>
License: MIT
Requires-Python: >=3.8
Requires-Dist: tqdm>=4.65.0
Requires-Dist: numpy>=1.24.3
